odoo/addons/sale_order_general_discount/README.rst
odoo/addons/sale_order_general_discount/__init__.py
odoo/addons/sale_order_general_discount/__manifest__.py
odoo/addons/sale_order_general_discount/i18n/de.po
odoo/addons/sale_order_general_discount/i18n/es.po
odoo/addons/sale_order_general_discount/i18n/it.po
odoo/addons/sale_order_general_discount/i18n/pt_BR.po
odoo/addons/sale_order_general_discount/i18n/sale_order_general_discount.pot
odoo/addons/sale_order_general_discount/i18n/zh_CN.po
odoo/addons/sale_order_general_discount/models/__init__.py
odoo/addons/sale_order_general_discount/models/product_product.py
odoo/addons/sale_order_general_discount/models/product_template.py
odoo/addons/sale_order_general_discount/models/res_partner.py
odoo/addons/sale_order_general_discount/models/sale_order.py
odoo/addons/sale_order_general_discount/models/sale_order_line.py
odoo/addons/sale_order_general_discount/readme/CONTRIBUTORS.md
odoo/addons/sale_order_general_discount/readme/DESCRIPTION.md
odoo/addons/sale_order_general_discount/readme/INSTALL.md
odoo/addons/sale_order_general_discount/readme/USAGE.md
odoo/addons/sale_order_general_discount/static/description/icon.png
odoo/addons/sale_order_general_discount/static/description/index.html
odoo/addons/sale_order_general_discount/tests/__init__.py
odoo/addons/sale_order_general_discount/tests/test_sale_order_general_discount.py
odoo/addons/sale_order_general_discount/views/product_view.xml
odoo/addons/sale_order_general_discount/views/res_partner_view.xml
odoo/addons/sale_order_general_discount/views/sale_order_view.xml
odoo_addon_sale_order_general_discount-19.0.1.0.0.2.dist-info/METADATA
odoo_addon_sale_order_general_discount-19.0.1.0.0.2.dist-info/WHEEL
odoo_addon_sale_order_general_discount-19.0.1.0.0.2.dist-info/top_level.txt
odoo_addon_sale_order_general_discount-19.0.1.0.0.2.dist-info/RECORD
